LICENSE
MANIFEST.in
README.rst
setup.cfg
setup.py
django_password_history_plus.egg-info/PKG-INFO
django_password_history_plus.egg-info/SOURCES.txt
django_password_history_plus.egg-info/dependency_links.txt
django_password_history_plus.egg-info/top_level.txt
password_histories/__init__.py
password_histories/admin.py
password_histories/apps.py
password_histories/models.py
password_histories/signals.py
password_histories/tests.py
password_histories/utils.py
password_histories/views.py
password_histories/migrations/0001_initial.py
password_histories/migrations/__init__.py